{"name":"refresh","event":[{"listen":"test","script":{"id":"73add022-30de-4fd2-a9a0-62d0679add7e","exec":["var jsonData = JSON.parse(responseBody);\r","\r","postman.setEnvironmentVariable(\"token\", jsonData.data.token);"],"type":"text\/javascript"}}],"protocolProfileBehavior":{"disableBodyPruning":true,"disabledSystemHeaders":{"accept":true}},"request":{"auth":{"type":"bearer","bearer":[{"key":"token","value":"{{token}}","type":"string"}]},"method":"GET","header":[{"key":"Accept","value":"application\/prs.doc.v1+json","type":"text"}],"body":{"mode":"formdata","formdata":[]},"url":{"raw":"{{url}}refresh","host":["{{url}}refresh"]}},"response":[]}